facebook/__init__.py
fb_errucha-1.0.0.dist-info/METADATA
fb_errucha-1.0.0.dist-info/WHEEL
fb_errucha-1.0.0.dist-info/entry_points.txt
fb_errucha-1.0.0.dist-info/top_level.txt
fb_errucha-1.0.0.dist-info/RECORD
