Metadata-Version: 2.1
Name: fb-errucha
Version: 1.0.0
Summary: Tools for facebook.
Author: Errucha
Author-email: masserucha@kontolodon.com
Requires-Dist: requests
Requires-Dist: bs4
